marcflow/__init__.py
marcflow/marcflow.py
marcflow-0.3.dist-info/LICENSE
marcflow-0.3.dist-info/WHEEL
marcflow-0.3.dist-info/METADATA
marcflow-0.3.dist-info/RECORD
