Metadata-Version: 2.1
Name: marcflow
Version: 0.3
Summary: A Python library for MARC data preprocessing
Author: zhv
Requires-Python: >=3.8
Classifier: Development Status :: 3 - Alpha
Classifier: Intended Audience :: Developers
Classifier: Programming Language :: Python :: 3
Classifier: License :: OSI Approved :: GNU General Public License v3 (GPLv3)
Classifier: Operating System :: OS Independent
Project-URL: Home, https://github.com/turricula/marcflow
